version_demo/__init__.py
version_demo/akg.py
version_de-0.1.3.dist-info/METADATA
version_de-0.1.3.dist-info/WHEEL
version_de-0.1.3.dist-info/top_level.txt
version_de-0.1.3.dist-info/RECORD
