Metadata-Version: 2.1
Name: version-de
Version: 0.1.3
Summary: Just demo for checking how is version work
Home-page: https://bitbucket.org/avneesh111995/mrchantintionpythonlibrary/
Author: ishaan.kumar
Author-email: ishaan.kumar@paytm.com
License: UNKNOWN
Platform: UNKNOWN
Classifier: Programming Language :: Python :: 3
Classifier: Operating System :: OS Independent
